{"name": "mercurian","children":[{"index":890,"P. Name":"Kepler-37 b","P. Habitable Class":"non-habitable","P. Mass (EU)":0.02,"P. Gravity (EU)":0.23,"P. Ts Mean (K)":678.4,"P. Period (days)":13.37},{"index":1041,"P. Name":"Kepler-106 b","P. Habitable Class":"non-habitable","P. Mass (EU)":0.15,"P. Gravity (EU)":0.22,"P. Ts Mean (K)":1047.3,"P. Period (days)":6.16},{"index":1118,"P. Name":"Kepler-138 b","P. Habitable Class":"non-habitable","P. Mass (EU)":0.07,"P. Gravity (EU)":0.2,"P. Ts Mean (K)":477.0,"P. Period (days)":10.31},{"index":1820,"P. Name":"Kepler-444 b","P. Habitable Class":"non-habitable","P. Mass (EU)":0.04,"P. Gravity (EU)":0.28,"P. Ts Mean (K)":962.5,"P. Period (days)":3.6},{"index":3124,"P. Name":"KIC-12557548 b","P. Habitable Class":"non-habitable","P. Mass (EU)":0.1,"P. Gravity (EU)":0.14,"P. Ts Mean (K)":null,"P. Period (days)":0.65}]}